pysharp/__init__.py
pysharp/connection.py
pysharp/util.py
pysharp-0.1.0.dist-info/METADATA
pysharp-0.1.0.dist-info/WHEEL
pysharp-0.1.0.dist-info/top_level.txt
pysharp-0.1.0.dist-info/RECORD
