Metadata-Version: 2.1
Name: pysharp
Version: 0.1.0
Summary: Async RPC connecting Python to C# and Unity3D
Home-page: https://github.com/rmst/pysharp
Author: Simon Ramstedt
Author-email: simonramstedt@gmail.com
License: UNKNOWN
Platform: UNKNOWN
